ivy_builder/__init__.py
ivy_builder/builder.py
ivy_builder/checkpoints.py
ivy_builder/dataset.py
ivy_builder/scheduler.py
ivy_builder/abstract/__init__.py
ivy_builder/abstract/data_loader.py
ivy_builder/abstract/network.py
ivy_builder/abstract/network_group.py
ivy_builder/abstract/trainer.py
ivy_builder/abstract/tuner.py
ivy_builder/data_loaders/__init__.py
ivy_builder/data_loaders/seq_data_loader.py
ivy_builder/data_loaders/specs/__init__.py
ivy_builder/data_loaders/specs/seq_data_loader_spec.py
ivy_builder/empty/__init__.py
ivy_builder/empty/data_loader.py
ivy_builder/empty/network.py
ivy_builder/empty/trainer.py
ivy_builder/specs/__init__.py
ivy_builder/specs/data_loader_spec.py
ivy_builder/specs/dataset_dirs.py
ivy_builder/specs/dataset_spec.py
ivy_builder/specs/network_spec.py
ivy_builder/specs/spec.py
ivy_builder/specs/trainer_spec.py
ivy_builder/specs/tuner_spec.py
ivy_builder-1.1.9.data/scripts/format_dataset_containers.py
ivy_builder-1.1.9.data/scripts/print_json_args.py
ivy_builder-1.1.9.data/scripts/remove_checkpoints.py
ivy_builder-1.1.9.data/scripts/reset_to_defaults.sh
ivy_builder_demos/__init__.py
ivy_builder_demos/full_example.py
ivy_builder_demos/simple_example.py
ivy_builder-1.1.9.dist-info/LICENSE
ivy_builder-1.1.9.dist-info/METADATA
ivy_builder-1.1.9.dist-info/WHEEL
ivy_builder-1.1.9.dist-info/top_level.txt
ivy_builder-1.1.9.dist-info/RECORD
