Metadata-Version: 2.1
Name: ivy-builder
Version: 1.1.9
Summary: Build custom Ivy training tasks with clear, hierarchical and robust user specifications.
Home-page: https://ivy-dl.org/builder
Author: Ivy Team
Author-email: ivydl.team@gmail.com
License: Apache 2.0
Project-URL: Docs, https://ivy-dl.org/builder/
Project-URL: Source, https://github.com/ivy-dl/builder
Platform: UNKNOWN
Classifier: License :: OSI Approved :: Apache Software License
License-File: LICENSE
Requires-Dist: ivy-core
